tano/__init__.py
tano/preprocessing.py
tano-0.0.2.dist-info/LICENSE
tano-0.0.2.dist-info/METADATA
tano-0.0.2.dist-info/WHEEL
tano-0.0.2.dist-info/top_level.txt
tano-0.0.2.dist-info/RECORD
