Metadata-Version: 2.1
Name: tano
Version: 0.0.2
Summary: Simplifying computer vision pre-processing and inference.
Home-page: https://github.com/winzurk/tano
Author: Zac Winzurk
Author-email: zwinzurk@asu.edu
License: UNKNOWN
Platform: UNKNOWN
Classifier: Programming Language :: Python :: 3
Classifier: License :: OSI Approved :: MIT License
Classifier: Operating System :: OS Independent
Requires-Python: >=3.6
